AUTHORS
LICENSE
MANIFEST.in
README.rst
setup.py
cmsplugin_contactform/__init__.py
cmsplugin_contactform/admin.py
cmsplugin_contactform/cms_plugins.py
cmsplugin_contactform/forms.py
cmsplugin_contactform/models.py
cmsplugin_contactform/urls.py
cmsplugin_contactform/views.py
cmsplugin_contactform/locale/hu/LC_MESSAGES/django.mo
cmsplugin_contactform/locale/hu/LC_MESSAGES/django.po
cmsplugin_contactform/static/js/contactform.js
cmsplugin_contactform/tests/__init__.py
cmsplugin_contactform/tests/forms.py
cmsplugin_contactform/tests/models.py
cmsplugin_contactform/tests/views.py
django_cms_contactform.egg-info/PKG-INFO
django_cms_contactform.egg-info/SOURCES.txt
django_cms_contactform.egg-info/dependency_links.txt
django_cms_contactform.egg-info/not-zip-safe
django_cms_contactform.egg-info/requires.txt
django_cms_contactform.egg-info/top_level.txt