Metadata-Version: 1.0
Name: django-cms-contactform
Version: 0.2
Summary: A simple contact us plugin for django-cms.
Home-page: https://github.com/nagyv/django-cms-contactform
Author: Viktor Nagy
Author-email: viktor.nagy@gmail.com
License: UNKNOWN
Download-URL: https://github.com/nagyv/django-cms-contactform/zipball/master
Platform: UNKNOWN
Classifier: Topic :: Internet :: WWW/HTTP :: Dynamic Content
Classifier: Intended Audience :: Developers
Classifier: License :: OSI Approved :: MIT License
Classifier: Programming Language :: Python
Classifier: Programming Language :: Python :: 2.6
Classifier: Programming Language :: Python :: 2.7
Classifier: Framework :: Django
Classifier: Development Status :: 4 - Beta
Classifier: Operating System :: OS Independent
